generic_encoders/__init__.py
generic_encoders/encoders/__init__.py
generic_encoders/encoders/avro_encoder.py
generic_encoders/encoders/base64_encoder.py
generic_encoders/encoders/composed_encoder.py
generic_encoders/encoders/csv_encoder.py
generic_encoders/encoders/dill_encoder.py
generic_encoders/encoders/encoder.py
generic_encoders/encoders/gzip_encoder.py
generic_encoders/encoders/json_encoder.py
generic_encoders/encoders/lz4_encoder.py
generic_encoders/encoders/msgpack_encoder.py
generic_encoders/encoders/no_op_encoder.py
generic_encoders/encoders/snappy_encoder.py
generic_encoders/encoders/text_encoder.py
generic_encoders-0.9.1.data/data/LICENSE
generic_encoders-0.9.1.data/data/README.md
generic_encoders-0.9.1.data/data/VERSION
generic_encoders-0.9.1.dist-info/LICENSE
generic_encoders-0.9.1.dist-info/METADATA
generic_encoders-0.9.1.dist-info/WHEEL
generic_encoders-0.9.1.dist-info/top_level.txt
generic_encoders-0.9.1.dist-info/RECORD
