Metadata-Version: 2.1
Name: generic-encoders
Version: 0.9.1
Summary: 
Home-page: https://github.com/mmontagna/generic-encoders
Author: Marco Montagna
Author-email: marcojoemontagna@gmail.com
License: Copyright (c) 2018 Marco Montagna
Requires-Dist: six (>=1.9.0)
Requires-Dist: lz4 (>=4.3.2)
Requires-Dist: dill (>=0.3.6)
Requires-Dist: msgpack (>=0.5.6)
Requires-Dist: simplejson (>=3.8.0)
Provides-Extra: all
Requires-Dist: python-snappy (~=0.5.3) ; extra == 'all'
Provides-Extra: dev
Requires-Dist: python-snappy (~=0.5.3) ; extra == 'dev'
Provides-Extra: snappy
Requires-Dist: python-snappy (~=0.5.3) ; extra == 'snappy'
